{
  "packages": [
    {
      "package": {
        "name": "vue-codemirror",
        "scope": "unscoped",
        "version": "6.1.1",
        "description": "CodeMirror code editor component for Vue",
        "keywords": [
          "vue-codemirror",
          "vue codemirror",
          "vue code editor",
          "web IDE vue"
        ],
        "date": "2022-08-27T19:38:24.292Z",
        "links": {
          "npm": "https://www.npmjs.com/package/vue-codemirror",
          "homepage": "https://github.surmon.me/vue-codemirror",
          "repository": "https://github.com/surmon-china/vue-codemirror",
          "bugs": "https://github.com/surmon-china/vue-codemirror/issues"
        },
        "author": {
          "name": "Surmon"
        },
        "publisher": {
          "username": "surmon",
          "email": "surmon.me@gmail.com"
        },
        "maintainers": [
          {
            "username": "surmon",
            "email": "surmon.me@gmail.com"
          }
        ]
      },
      "score": {
        "final": 0.39742574561299426,
        "detail": {
          "quality": 0.6478947567635519,
          "popularity": 0.25682394987033025,
          "maintenance": 0.32333981751232327
        }
      },
      "searchScore": 0.000023093175
    },
    {
      "package": {
        "name": "vue-awesome-swiper",
        "scope": "unscoped",
        "version": "5.0.1",
        "description": "Swiper component for Vue",
        "keywords": [
          "vue swiper",
          "vue awesome swiper",
          "vue carrousel",
          "carrousel",
          "swiper"
        ],
        "date": "2022-03-19T04:09:09.961Z",
        "links": {
          "npm": "https://www.npmjs.com/package/vue-awesome-swiper",
          "homepage": "https://github.surmon.me/vue-awesome-swiper",
          "repository": "https://github.com/surmon-china/vue-awesome-swiper",
          "bugs": "https://github.com/surmon-china/vue-awesome-swiper/issues"
        },
        "author": {
          "name": "Surmon",
          "url": "https://github.com/surmon-china"
        },
        "publisher": {
          "username": "surmon",
          "email": "surmon.me@gmail.com"
        },
        "maintainers": [
          {
            "username": "surmon",
            "email": "surmon.me@gmail.com"
          }
        ]
      },
      "score": {
        "final": 0.3180748984686214,
        "detail": {
          "quality": 0.6159101572185833,
          "popularity": 0.3011272317394635,
          "maintenance": 0.07973520055495484
        }
      },
      "searchScore": 0.0000023947705
    },
    {
      "package": {
        "name": "vue-quill-editor",
        "scope": "unscoped",
        "version": "3.0.6",
        "description": "Quill editor component for Vue",
        "keywords": [
          "vue-quill-editor",
          "vue quill",
          "vue text editor",
          "vue rich text editor",
          "vue web editor",
          "vue editor"
        ],
        "date": "2018-04-09T09:45:01.816Z",
        "links": {
          "npm": "https://www.npmjs.com/package/vue-quill-editor",
          "homepage": "https://github.com/surmon-china/vue-quill-editor#readme",
          "repository": "https://github.com/surmon-china/vue-quill-editor",
          "bugs": "https://github.com/surmon-china/vue-quill-editor/issues"
        },
        "author": {
          "name": "Surmon",
          "email": "surmon@foxmail.com",
          "url": "https://surmon.me",
          "username": "surmon"
        },
        "publisher": {
          "username": "surmon",
          "email": "surmon@foxmail.com"
        },
        "maintainers": [
          {
            "username": "surmon",
            "email": "surmon@foxmail.com"
          }
        ]
      },
      "score": {
        "final": 0.30660411704503027,
        "detail": {
          "quality": 0.6457664827989255,
          "popularity": 0.2653961956740888,
          "maintenance": 0.05710143919834736
        }
      },
      "searchScore": 0.000001256854
    },
    {
      "package": {
        "name": "vue-touch-ripple",
        "scope": "unscoped",
        "version": "4.1.1",
        "description": "Touch ripple component for Vue",
        "keywords": [
          "vue touch ripple",
          "vue ripple",
          "vue touch"
        ],
        "date": "2022-07-27T14:33:49.495Z",
        "links": {
          "npm": "https://www.npmjs.com/package/vue-touch-ripple",
          "homepage": "https://github.surmon.me/vue-touch-ripple",
          "repository": "https://github.com/surmon-china/vue-touch-ripple",
          "bugs": "https://github.com/surmon-china/vue-touch-ripple/issues"
        },
        "author": {
          "name": "Surmon"
        },
        "publisher": {
          "username": "surmon",
          "email": "surmon.me@gmail.com"
        },
        "maintainers": [
          {
            "username": "surmon",
            "email": "surmon.me@gmail.com"
          }
        ]
      },
      "score": {
        "final": 0.3352195268688626,
        "detail": {
          "quality": 0.6360726679378873,
          "popularity": 0.08922511530909502,
          "maintenance": 0.32333981751232327
        }
      },
      "searchScore": 9.794428e-7
    },
    {
      "package": {
        "name": "@videojs-player/vue",
        "scope": "videojs-player",
        "version": "1.0.0",
        "description": "Video.js component for Vue",
        "keywords": [
          "vue-video-player",
          "vue video player",
          "video player",
          "vue player",
          "vue video"
        ],
        "date": "2022-08-14T16:14:41.126Z",
        "links": {
          "npm": "https://www.npmjs.com/package/%40videojs-player%2Fvue",
          "homepage": "https://github.surmon.me/videojs-player",
          "repository": "https://github.com/surmon-china/videojs-player",
          "bugs": "https://github.com/surmon-china/videojs-player/issues"
        },
        "author": {
          "name": "Surmon"
        },
        "publisher": {
          "username": "surmon",
          "email": "surmon.me@gmail.com"
        },
        "maintainers": [
          {
            "username": "surmon",
            "email": "surmon.me@gmail.com"
          }
        ]
      },
      "score": {
        "final": 0.3152682763223521,
        "detail": {
          "quality": 0.5862110031571032,
          "popularity": 0.06573298419248497,
          "maintenance": 0.33256694545100407
        }
      },
      "searchScore": 3.6735085e-7
    },
    {
      "package": {
        "name": "@videojs-player/react",
        "scope": "videojs-player",
        "version": "1.0.0",
        "description": "Video.js component for React",
        "keywords": [
          "react-video-player",
          "react video player",
          "video player",
          "react player",
          "react video"
        ],
        "date": "2022-08-14T16:20:24.497Z",
        "links": {
          "npm": "https://www.npmjs.com/package/%40videojs-player%2Freact",
          "homepage": "https://github.surmon.me/videojs-player",
          "repository": "https://github.com/surmon-china/videojs-player",
          "bugs": "https://github.com/surmon-china/videojs-player/issues"
        },
        "author": {
          "name": "Surmon"
        },
        "publisher": {
          "username": "surmon",
          "email": "surmon.me@gmail.com"
        },
        "maintainers": [
          {
            "username": "surmon",
            "email": "surmon.me@gmail.com"
          }
        ]
      },
      "score": {
        "final": 0.30738218179861687,
        "detail": {
          "quality": 0.5871075201441572,
          "popularity": 0.04557378113491787,
          "maintenance": 0.329426006737567
        }
      },
      "searchScore": 2.2646687e-7
    },
    {
      "package": {
        "name": "vue-video-player",
        "scope": "unscoped",
        "version": "6.0.0",
        "description": "Video.js component for Vue",
        "keywords": [
          "vue-video-player",
          "vue video player",
          "video player",
          "vue player",
          "vue video"
        ],
        "date": "2022-08-14T15:59:42.393Z",
        "links": {
          "npm": "https://www.npmjs.com/package/vue-video-player",
          "homepage": "https://github.com/surmon-china/videojs-player",
          "repository": "https://github.com/surmon-china/videojs-player",
          "bugs": "https://github.com/surmon-china/videojs-player/issues"
        },
        "author": {
          "name": "Surmon"
        },
        "publisher": {
          "username": "surmon",
          "email": "surmon.me@gmail.com"
        },
        "maintainers": [
          {
            "username": "surmon",
            "email": "surmon.me@gmail.com"
          }
        ]
      },
      "score": {
        "final": 0.2585704352060299,
        "detail": {
          "quality": 0.5306523456556157,
          "popularity": 0.17074055063717192,
          "maintenance": 0.113187253675243
        }
      },
      "searchScore": 7.817995e-8
    },
    {
      "package": {
        "name": "vuniversal",
        "scope": "unscoped",
        "version": "0.0.13",
        "description": "Create vue universal app",
        "keywords": [
          "vue",
          "ssr",
          "universal"
        ],
        "date": "2020-05-14T03:36:52.923Z",
        "links": {
          "npm": "https://www.npmjs.com/package/vuniversal",
          "homepage": "https://github.com/surmon-china/vuniversal#readme",
          "repository": "https://github.com/surmon-china/vuniversal",
          "bugs": "https://github.com/surmon-china/vuniversal/issues"
        },
        "author": {
          "name": "Surmon",
          "email": "surmon@foxmail.com",
          "url": "https://github.com/surmon-china",
          "username": "surmon"
        },
        "publisher": {
          "username": "surmon",
          "email": "surmon@foxmail.com"
        },
        "maintainers": [
          {
            "username": "surmon",
            "email": "surmon@foxmail.com"
          }
        ]
      },
      "flags": {
        "unstable": true
      },
      "score": {
        "final": 0.2602405886474793,
        "detail": {
          "quality": 0.7982986001296432,
          "popularity": 0.0021871568261851203,
          "maintenance": 0.05710143919834736
        }
      },
      "searchScore": 2.1417325e-8
    },
    {
      "package": {
        "name": "mongodb-data-api",
        "scope": "unscoped",
        "version": "0.4.0",
        "description": "MongoDB atlas data API SDK for Node.js",
        "keywords": [
          "MongoDB data API",
          "MongoDB cloud data API",
          "MongoDB Atlas data API SDK"
        ],
        "date": "2022-11-23T19:54:56.217Z",
        "links": {
          "npm": "https://www.npmjs.com/package/mongodb-data-api",
          "homepage": "https://github.com/surmon-china/mongodb-data-api#readme",
          "repository": "https://github.com/surmon-china/mongodb-data-api",
          "bugs": "https://github.com/surmon-china/mongodb-data-api/issues"
        },
        "author": {
          "name": "Surmon"
        },
        "publisher": {
          "username": "surmon",
          "email": "surmon.me@gmail.com"
        },
        "maintainers": [
          {
            "username": "surmon",
            "email": "surmon.me@gmail.com"
          }
        ]
      },
      "flags": {
        "unstable": true
      },
      "score": {
        "final": 0.2507693355588857,
        "detail": {
          "quality": 0.4156308442044158,
          "popularity": 0.02743627247123106,
          "maintenance": 0.3327925340932289
        }
      },
      "searchScore": 1.24449855e-8
    },
    {
      "package": {
        "name": "vue-drag-zone",
        "scope": "unscoped",
        "version": "2.0.0-rc1",
        "description": "Drag Zone component for Vue",
        "keywords": [
          "vue-drag-zone",
          "vue drag dom",
          "vue drag size",
          "vue drag"
        ],
        "date": "2018-04-11T08:07:39.500Z",
        "links": {
          "npm": "https://www.npmjs.com/package/vue-drag-zone",
          "homepage": "https://github.com/surmon-china/vue-drag-zone#readme",
          "repository": "https://github.com/surmon-china/vue-drag-zone",
          "bugs": "https://github.com/surmon-china/vue-drag-zone/issues"
        },
        "author": {
          "name": "Surmon",
          "email": "surmon@foxmail.com",
          "url": "http://surmon.me",
          "username": "surmon"
        },
        "publisher": {
          "username": "surmon",
          "email": "surmon@foxmail.com"
        },
        "maintainers": [
          {
            "username": "surmon",
            "email": "surmon@foxmail.com"
          }
        ]
      },
      "score": {
        "final": 0.22213252719515927,
        "detail": {
          "quality": 0.6457664827989255,
          "popularity": 0.024048796103028843,
          "maintenance": 0.05710143919834736
        }
      },
      "searchScore": 3.1478589e-9
    },
    {
      "package": {
        "name": "@surmon-china/libundler",
        "scope": "surmon-china",
        "version": "2.3.0",
        "description": "Universal JavaScript library bundler",
        "keywords": [
          "JavaScript bundler",
          "TypeScript bundler",
          "zero config bundler",
          "react component bundler",
          "rollup",
          "webpack"
        ],
        "date": "2022-06-11T19:33:30.966Z",
        "links": {
          "npm": "https://www.npmjs.com/package/%40surmon-china%2Flibundler"
        },
        "author": {
          "name": "Surmon"
        },
        "publisher": {
          "username": "surmon",
          "email": "surmon.me@gmail.com"
        },
        "maintainers": [
          {
            "username": "surmon",
            "email": "surmon.me@gmail.com"
          }
        ]
      },
      "score": {
        "final": 0.22453790889001918,
        "detail": {
          "quality": 0.46376641569929433,
          "popularity": 0.021057924043356435,
          "maintenance": 0.22296488790016036
        }
      },
      "searchScore": 2.935585e-9
    },
    {
      "package": {
        "name": "simple-netease-cloud-music",
        "scope": "unscoped",
        "version": "0.5.2",
        "description": "网易云音乐 API for node.js",
        "keywords": [
          "网易云音乐",
          "网易云 API",
          "网易云 nodejs",
          "Netease Cloud Music"
        ],
        "date": "2020-12-20T16:06:01.478Z",
        "links": {
          "npm": "https://www.npmjs.com/package/simple-netease-cloud-music",
          "homepage": "https://github.com/surmon-china/simple-netease-cloud-music#readme",
          "repository": "https://github.com/surmon-china/simple-netease-cloud-music",
          "bugs": "https://github.com/surmon-china/simple-netease-cloud-music/issues"
        },
        "author": {
          "name": "Surmon",
          "email": "surmon@foxmail.com",
          "url": "https://github.com/surmon-china",
          "username": "surmon"
        },
        "publisher": {
          "username": "surmon",
          "email": "surmon@foxmail.com"
        },
        "maintainers": [
          {
            "username": "surmon",
            "email": "surmon@foxmail.com"
          }
        ]
      },
      "flags": {
        "unstable": true
      },
      "score": {
        "final": 0.18116083641348452,
        "detail": {
          "quality": 0.5085576103791594,
          "popularity": 0.024594427372328934,
          "maintenance": 0.05710143919834736
        }
      },
      "searchScore": 2.1066354e-10
    },
    {
      "package": {
        "name": "wonderful-bing-wallpaper",
        "scope": "unscoped",
        "version": "0.3.4",
        "description": "Simple bing daily wallpaper API lib for node.js",
        "keywords": [
          "bing",
          "bing wallpaper",
          "bing wallpaper api",
          "daily-wallpaper",
          "bing-daily-wallpaper",
          "wonderful-bing-daily-wallpaper"
        ],
        "date": "2020-03-28T14:49:29.400Z",
        "links": {
          "npm": "https://www.npmjs.com/package/wonderful-bing-wallpaper",
          "homepage": "https://github.com/surmon-china/wonderful-bing-wallpaper#readme",
          "repository": "https://github.com/surmon-china/wonderful-bing-wallpaper",
          "bugs": "https://github.com/surmon-china/wonderful-bing-wallpaper/issues"
        },
        "author": {
          "name": "Surmon",
          "email": "surmon@foxmail.com",
          "url": "https://github.com/surmon-china",
          "username": "surmon"
        },
        "publisher": {
          "username": "surmon",
          "email": "surmon@foxmail.com"
        },
        "maintainers": [
          {
            "username": "surmon",
            "email": "surmon@foxmail.com"
          }
        ]
      },
      "flags": {
        "unstable": true
      },
      "score": {
        "final": 0.17963101519245842,
        "detail": {
          "quality": 0.5085576103791594,
          "popularity": 0.020223509597968682,
          "maintenance": 0.05710143919834736
        }
      },
      "searchScore": 1.7811189e-10
    },
    {
      "package": {
        "name": "veact",
        "scope": "unscoped",
        "version": "0.1.4",
        "description": "Mutable state enhancer library for @react by @vue/reactivity",
        "keywords": [
          "React mutable state lib",
          "React vue state",
          "React composition API",
          "React state library"
        ],
        "date": "2022-01-17T08:42:19.200Z",
        "links": {
          "npm": "https://www.npmjs.com/package/veact",
          "homepage": "https://github.com/veactjs/veact#readme",
          "repository": "https://github.com/veactjs/veact",
          "bugs": "https://github.com/veactjs/veact/issues"
        },
        "author": {
          "name": "Surmon"
        },
        "publisher": {
          "username": "surmon",
          "email": "surmon.me@gmail.com"
        },
        "maintainers": [
          {
            "username": "surmon",
            "email": "surmon.me@gmail.com"
          }
        ]
      },
      "flags": {
        "unstable": true
      },
      "score": {
        "final": 0.17462868626310538,
        "detail": {
          "quality": 0.4471201700180834,
          "popularity": 0.0025059899181293687,
          "maintenance": 0.113187253675243
        }
      },
      "searchScore": 8.936661e-11
    },
    {
      "package": {
        "name": "veact-use",
        "scope": "unscoped",
        "version": "0.1.3",
        "description": "Collection of Veact Hooks",
        "keywords": [
          "React mutable state lib",
          "React vue state",
          "React composition API",
          "Veact Hooks"
        ],
        "date": "2021-07-26T20:55:26.788Z",
        "links": {
          "npm": "https://www.npmjs.com/package/veact-use",
          "homepage": "https://github.com/veactjs/veact-use#readme",
          "repository": "https://github.com/veactjs/veact-use",
          "bugs": "https://github.com/veactjs/veact-use/issues"
        },
        "author": {
          "name": "Surmon"
        },
        "publisher": {
          "username": "surmon",
          "email": "surmon@foxmail.com"
        },
        "maintainers": [
          {
            "username": "surmon",
            "email": "surmon@foxmail.com"
          }
        ]
      },
      "flags": {
        "unstable": true
      },
      "score": {
        "final": 0.1745136931302321,
        "detail": {
          "quality": 0.4471201700180834,
          "popularity": 0.0021774381099200118,
          "maintenance": 0.113187253675243
        }
      },
      "searchScore": 8.8179936e-11
    },
    {
      "package": {
        "name": "naivebayes",
        "scope": "unscoped",
        "version": "0.5.0",
        "description": "Naive Bayes Classifier for node.js.",
        "date": "2017-04-24T03:24:49.812Z",
        "links": {
          "npm": "https://www.npmjs.com/package/naivebayes"
        },
        "author": {
          "name": "Surmon"
        },
        "publisher": {
          "username": "surmon",
          "email": "surmon@foxmail.com"
        },
        "maintainers": [
          {
            "username": "surmon",
            "email": "surmon@foxmail.com"
          }
        ]
      },
      "flags": {
        "unstable": true
      },
      "score": {
        "final": 0.16872444420480223,
        "detail": {
          "quality": 0.490827312972874,
          "popularity": 0.004259275981481371,
          "maintenance": 0.05710143919834736
        }
      },
      "searchScore": 6.2251385e-11
    },
    {
      "package": {
        "name": "@surmon/libundler",
        "scope": "surmon",
        "version": "0.1.0",
        "description": "Universal JavaScript library bundler",
        "keywords": [
          "JavaScript bundler",
          "TypeScript bundler",
          "zero config bundler",
          "react component bundler",
          "rollup",
          "webpack"
        ],
        "date": "2022-07-31T20:45:04.009Z",
        "links": {
          "npm": "https://www.npmjs.com/package/%40surmon%2Flibundler",
          "homepage": "https://github.com/surmon-china/libundler#readme",
          "repository": "https://github.com/surmon-china/libundler",
          "bugs": "https://github.com/surmon-china/libundler/issues"
        },
        "author": {
          "name": "Surmon"
        },
        "publisher": {
          "username": "surmon",
          "email": "surmon.me@gmail.com"
        },
        "maintainers": [
          {
            "username": "surmon",
            "email": "surmon.me@gmail.com"
          }
        ]
      },
      "flags": {
        "unstable": true
      },
      "score": {
        "final": 0.1682150094915107,
        "detail": {
          "quality": 0.3453571715721633,
          "popularity": 0.01809510604910783,
          "maintenance": 0.16649877400764
        }
      },
      "searchScore": 6.146753e-11
    },
    {
      "package": {
        "name": "emoji-233333",
        "scope": "unscoped",
        "version": "0.3.2",
        "description": "233333",
        "keywords": [
          "emoji canvas",
          "emoji rain",
          "233333",
          "emoji",
          "表情雨"
        ],
        "date": "2020-10-17T14:40:46.264Z",
        "links": {
          "npm": "https://www.npmjs.com/package/emoji-233333",
          "homepage": "https://github.com/surmon-china/emoji-233333#readme",
          "repository": "https://github.com/surmon-china/emoji-233333",
          "bugs": "https://github.com/surmon-china/emoji-233333/issues"
        },
        "author": {
          "name": "Surmon",
          "url": "https://github.com/surmon-china"
        },
        "publisher": {
          "username": "surmon",
          "email": "surmon@foxmail.com"
        },
        "maintainers": [
          {
            "username": "surmon",
            "email": "surmon@foxmail.com"
          }
        ]
      },
      "flags": {
        "unstable": true
      },
      "score": {
        "final": 0.14654112408979889,
        "detail": {
          "quality": 0.40341529856060865,
          "popularity": 0.061458383169751996,
          "maintenance": 0.01144600117772312
        }
      },
      "searchScore": 2.3837831e-11
    },
    {
      "package": {
        "name": "vue-stacks-editor",
        "scope": "unscoped",
        "version": "0.0.1",
        "description": "Stacks editor for Vue.",
        "keywords": [
          "vue markdown editor",
          "StackOverflow editor",
          "StackOverflow markdown editor"
        ],
        "date": "2022-07-20T14:57:21.450Z",
        "links": {
          "npm": "https://www.npmjs.com/package/vue-stacks-editor"
        },
        "author": {
          "name": "Surmon"
        },
        "publisher": {
          "username": "surmon",
          "email": "surmon.me@gmail.com"
        },
        "maintainers": [
          {
            "username": "surmon",
            "email": "surmon.me@gmail.com"
          }
        ]
      },
      "flags": {
        "unstable": true
      },
      "score": {
        "final": 0.14645102509166377,
        "detail": {
          "quality": 0.29252664056061317,
          "popularity": 0.0011956057737309842,
          "maintenance": 0.16649877400764
        }
      },
      "searchScore": 7.23777e-12
    },
    {
      "package": {
        "name": "player.ts",
        "scope": "unscoped",
        "version": "0.0.1",
        "date": "2022-07-31T20:28:43.940Z",
        "links": {
          "npm": "https://www.npmjs.com/package/player.ts"
        },
        "author": {
          "name": "Surmon"
        },
        "publisher": {
          "username": "surmon",
          "email": "surmon.me@gmail.com"
        },
        "maintainers": [
          {
            "username": "surmon",
            "email": "surmon.me@gmail.com"
          }
        ]
      },
      "flags": {
        "unstable": true
      },
      "score": {
        "final": 0.14499658907481833,
        "detail": {
          "quality": 0.28776881987512437,
          "popularity": 0.0011182063131629154,
          "maintenance": 0.16649877400764
        }
      },
      "searchScore": 6.3004064e-12
    }
  ],
  "downloads": {
    "mongodb-data-api": 3361,
    "vue-drag-zone": 3258,
    "@videojs-player/vue": 116345,
    "emoji-233333": 1995,
    "simple-netease-cloud-music": 2535,
    "wonderful-bing-wallpaper": 1940,
    "vue-quill-editor": 3805801,
    "player.ts": 106,
    "veact": 655,
    "vue-stacks-editor": 117,
    "@surmon-china/libundler": 3386,
    "@videojs-player/react": 13928,
    "naivebayes": 891,
    "vuniversal": 506,
    "vue-codemirror": 2881892,
    "vue-awesome-swiper": 7751487,
    "@surmon/libundler": 110,
    "vue-video-player": 1046688,
    "vue-touch-ripple": 10739,
    "veact-use": 480
  }
}